aiohttp_json_rpc/__init__.py
aiohttp_json_rpc/client.py
aiohttp_json_rpc/communicaton.py
aiohttp_json_rpc/decorators.py
aiohttp_json_rpc/exceptions.py
aiohttp_json_rpc/protocol.py
aiohttp_json_rpc/pytest.py
aiohttp_json_rpc/rpc.py
aiohttp_json_rpc/threading.py
aiohttp_json_rpc/auth/__init__.py
aiohttp_json_rpc/auth/django.py
aiohttp_json_rpc/auth/passwd.py
aiohttp_json_rpc/django/__init__.py
aiohttp_json_rpc/django/apps.py
aiohttp_json_rpc/django/models.py
aiohttp_json_rpc/django/utils.py
aiohttp_json_rpc/django/static/.rpc.js.swp
aiohttp_json_rpc/django/static/rpc.js
aiohttp_json_rpc-0.13.3.dist-info/LICENSE.txt
aiohttp_json_rpc-0.13.3.dist-info/METADATA
aiohttp_json_rpc-0.13.3.dist-info/WHEEL
aiohttp_json_rpc-0.13.3.dist-info/entry_points.txt
aiohttp_json_rpc-0.13.3.dist-info/top_level.txt
aiohttp_json_rpc-0.13.3.dist-info/RECORD
