Metadata-Version: 1.2
Name: aiohttp-json-rpc
Version: 0.13.3
Summary: Implementation JSON-RPC 2.0 server and client using aiohttp on top of websockets transport
Home-page: https://github.com/pengutronix/aiohttp-json-rpc/
Author: Florian Scherf
Author-email: f.scherf@pengutronix.de
License: Apache 2.0
Keywords: aiohttp,asyncio,websockets,json-rpc
Platform: UNKNOWN
Classifier: Development Status :: 5 - Production/Stable
Classifier: Intended Audience :: Developers
Classifier: License :: OSI Approved :: Apache Software License
Classifier: Operating System :: OS Independent
Classifier: Programming Language :: Python
Classifier: Programming Language :: Python :: 3
Classifier: Programming Language :: Python :: 3 :: Only
Classifier: Programming Language :: Python :: 3.5
Classifier: Programming Language :: Python :: 3.6
Classifier: Programming Language :: Python :: Implementation :: CPython
Classifier: Programming Language :: Python :: Implementation :: PyPy
Classifier: Topic :: Internet :: WWW/HTTP
Requires-Python: >=3.5
